.coveragerc
.eslintrc.js
Apache-License-2.0.txt
CONTRIBUTORS
COPYING
Jenkinsfile
LICENSE-MERGELY.html
LICENSE.md
MANIFEST.in
MIT-Permissive-License.txt
README.rst
conftest.py
dev_requirements.txt
development.ini
pytest.ini
pytype_requirements.txt
requirements.txt
setup.cfg
setup.py
tox.ini
Kallithea.egg-info/PKG-INFO
Kallithea.egg-info/SOURCES.txt
Kallithea.egg-info/dependency_links.txt
Kallithea.egg-info/entry_points.txt
Kallithea.egg-info/not-zip-safe
Kallithea.egg-info/requires.txt
Kallithea.egg-info/top_level.txt
docs/Makefile
docs/conf.py
docs/contributing.rst
docs/index.rst
docs/installation.rst
docs/installation_iis.rst
docs/installation_puppet.rst
docs/installation_win.rst
docs/installation_win_old.rst
docs/make.bat
docs/overview.rst
docs/readme.rst
docs/setup.rst
docs/upgrade.rst
docs/administrator_guide/auth.rst
docs/administrator_guide/vcs_setup.rst
docs/api/api.rst
docs/api/models.rst
docs/dev/dbmigrations.rst
docs/dev/i18n.rst
docs/theme/nature/layout.html
docs/theme/nature/theme.conf
docs/theme/nature/static/kallithea-logo.svg
docs/theme/nature/static/nature.css_t
docs/theme/nature/static/pygments.css
docs/usage/backup.rst
docs/usage/customization.rst
docs/usage/debugging.rst
docs/usage/email.rst
docs/usage/general.rst
docs/usage/performance.rst
docs/usage/statistics.rst
docs/usage/troubleshooting.rst
docs/usage/vcs_notes.rst
init.d/celeryd-upstart.conf
init.d/kallithea-daemon-arch
init.d/kallithea-daemon-debian
init.d/kallithea-daemon-gentoo
init.d/kallithea-daemon-redhat
init.d/kallithea-upstart.conf
init.d/supervisord.conf
kallithea/__init__.py
kallithea/alembic/env.py
kallithea/alembic/script.py.mako
kallithea/alembic/versions/151b4a4e8c48_db_migration_step_after_93834966ae01_.py
kallithea/alembic/versions/4851d15bc437_db_migration_step_after_95c01895c006_.py
kallithea/alembic/versions/7ba0d2cad930_hooks_migrate_internal_hooks_to_.py
kallithea/alembic/versions/9358dc3d6828_drop_sqlalchemy_migrate_support.py
kallithea/alembic/versions/a020f7044fd6_rename_hooks.py
kallithea/alembic/versions/a0a1bf09c143_db_add_ui_composite_index_and_drop_.py
kallithea/alembic/versions/ad357ccd9521_drop_locking.py
kallithea/alembic/versions/b74907136bc1_create_table_for_ssh_keys.py
