Metadata-Version: 1.1
Name: Kallithea
Version: 0.7.0
Summary: Kallithea is a fast and powerful management tool for Mercurial and Git with a built in push/pull server, full text search and code-review.
Home-page: https://kallithea-scm.org/
Author: Various Authors
Author-email: kallithea@sfconservancy.org
License: GPLv3
Keywords: kallithea mercurial git code review repo groups ldap repository management hgweb replacement hgwebdir gitweb replacement serving hgweb
Platform: UNKNOWN
Classifier: Development Status :: 4 - Beta
Classifier: Environment :: Web Environment
Classifier: Framework :: Pylons
Classifier: Intended Audience :: Developers
Classifier: License :: OSI Approved :: GNU General Public License (GPL)
Classifier: Operating System :: OS Independent
Classifier: Programming Language :: Python :: 3.6
Classifier: Programming Language :: Python :: 3.7
Classifier: Programming Language :: Python :: 3.8
Classifier: Topic :: Software Development :: Version Control
